[
  {
    "id": 2,
    "hostel_name": "S.S Ladies Hostel Near Municipality",
    "owner_name": "Saju",
    "price": "6000",
    "contact_no": "9745354655",
    "whatsapp_no": "9745354655",
    "food": "",
    "deposit": "1000",
    "distance": "850 m",
    "gender": "Female",
    "seats": {
      "boys": "0",
      "girls": "20"
    },
    "images": ["img_67.jpg", "ss ladies.jpg"],
    "links": ["https://maps.app.goo.gl/o9VU14fgNUo5bfoK9"],
    "common_details": {
      "wifi": "Yes",
      "washing_machines": "No",
      "filtered_water": "No",
      "hot_water": "No",
      "parking": "Yes",
      "security": "Yes",
      "cctv": "Yes",
      "iron_box": "Yes",
      "common_bathroom": "Yes",
      "NOTA": "No"
    },
    "single_room": {
      "available": "No",
      "price": "N/A",
      "bed_type": {
        "single": {
          "available": "No"
        },
        "double": {
          "available": "No"
        }
      },
      "options_available": {
        "ac": "No",
        "furniture": "No",
        "private_bathroom": "No"
      }
    },
    "shared_room": {
      "available": "Yes",
      "price": "5500",
      "bed_type": {
        "single": {
          "available": "No"
        },
        "double": {
          "available": "No"
        }
      },
      "options_available": {
        "ac": "No",
        "furniture": "Yes",
        "private_bathroom": "Yes"
      }
    }
  },
  {
    "id": 4,
    "hostel_name": "S.S Ladies Hostel - Near Attakulam",
    "owner_name": "Saju",
    "price": "6000",
    "contact_no": "9745354655",
    "whatsapp_no": "9745354655",
    "food": "",
    "deposit": "1000",
    "distance": "850 m",
    "gender": "Female",
    "seats": {
      "boys": "0",
      "girls": "20"
    },
    "images": ["img_1.jpg", "img_2.jpg", "img_3.jpg", "img_4.jpg", "img_6.jpg"],
    "links": ["https://maps.app.goo.gl/89wGiYsovkXWwCh38"],
    "common_details": {
      "wifi": "Yes",
      "washing_machines": "No",
      "filtered_water": "No",
      "hot_water": "No",
      "parking": "Yes",
      "security": "Yes",
      "cctv": "Yes",
      "iron_box": "Yes",
      "common_bathroom": "Yes",
      "NOTA": "No"
    },
    "single_room": {
      "available": "No",
      "price": "N/A",
      "bed_type": {
        "single": {
          "available": "No"
        },
        "double": {
          "available": "No"
        }
      },
      "options_available": {
        "ac": "No",
        "furniture": "No",
        "private_bathroom": "No"
      }
    },
    "shared_room": {
      "available": "Yes",
      "price": "5500",
      "bed_type": {
        "single": {
          "available": "No"
        },
        "double": {
          "available": "No"
        }
      },
      "options_available": {
        "ac": "No",
        "furniture": "Yes",
        "private_bathroom": "Yes"
      }
    }
  },
  {
    "id": 1,
    "hostel_name": "Home Stay [ Male ]",
    "owner_name": "Shella Mohan",
    "price": "6000",
    "contact_no": "8281603395",
    "whatsapp_no": "8281603395",
    "food": "",
    "deposit": "2000",
    "distance": "1.3km",
    "gender": "Male",
    "seats": {
      "boys": "10"
    },
    "images": ["img_21.jpg", "img_22.jpg"],
    "links": [
      "https://www.google.com/maps/place/8%C2%B041'43.4%22N+76%C2%B048'42.9%22E/@8.6953942",
      "76.8093418",
      "17z/data=!3m1!4b1!4m4!3m3!8m2!3d8.6953889!4d76.8119167?entry=ttu"
    ],
    "common_details": {
      "wifi": "No",
      "washing_machines": "No",
      "filtered_water": "Yes",
      "hot_water": "No",
      "parking": "Yes",
      "security": "Yes",
      "cctv": "No",
      "iron_box": "No",
      "common_bathroom": "Yes",
      "NOTA": "No"
    },
    "single_room": {
      "available": "Yes",
      "price": "--",
      "bed_type": {
        "single": {
          "available": "No"
        },
        "double": {
          "available": "No"
        }
      },
      "options_available": {
        "ac": "No",
        "furniture": "Yes",
        "private_bathroom": "Yes"
      }
    },
    "shared_room": {
      "available": "Yes",
      "price": "5500",
      "bed_type": {
        "single": {
          "available": "Yes"
        },
        "double": {
          "available": "No"
        }
      },
      "options_available": {
        "ac": "No",
        "furniture": "Yes",
        "private_bathroom": "Yes"
      }
    }
  },

  {
    "id": 8,
    "hostel_name": "Sreelekshmi Ladies Hostel",
    "owner_name": "Lathika K",
    "price": "7000",
    "contact_no": "8078313518",
    "whatsapp_no": "8078313518",
    "food": "",
    "deposit": "3000",
    "distance": "1.3km",
    "gender": "Female",
    "seats": {
      "boys": "0",
      "girls": "15"
    },
    "images": ["img_62.jpg", "img_63.jpg"],
    "links": ["https://maps.app.goo.gl/ySBPJTt7X7hWtZmz6?g_st=aw"],
    "common_details": {
      "wifi": "No",
      "washing_machines": "No",
      "filtered_water": "No",
      "hot_water": "Yes",
      "parking": "Yes",
      "security": "Yes",
      "cctv": "Yes",
      "iron_box": "No",
      "common_bathroom": "Yes",
      "NOTA": "No"
    },
    "single_room": {
      "available": "Yes",
      "price": "7000",
      "bed_type": {
        "single": {
          "available": "yes"
        },
        "double": {
          "available": "No"
        }
      },
      "options_available": {
        "ac": "No",
        "furniture": "Yes",
        "private_bathroom": "Yes"
      }
    },
    "shared_room": {
      "available": "Yes",
      "price": "5000",
      "bed_type": {
        "single": {
          "available": "Yes"
        },
        "double": {
          "available": "No"
        }
      },
      "options_available": {
        "ac": "No",
        "furniture": "Yes",
        "private_bathroom": "Yes"
      }
    }
  },
  {
    "id": 7,
    "hostel_name": "Home Stay [ Females ]",
    "owner_name": "Shella Mohan",
    "price": "5800",
    "contact_no": "8281603395",
    "whatsapp_no": "8281603395",
    "food": "",
    "deposit": "2000",
    "distance": "1.3km",
    "gender": "Female",
    "seats": {
      "girls": "10"
    },
    "images": ["img_21.jpg", "img_22.jpg"],
    "links": [
      "https://www.google.com/maps/place/8%C2%B041'43.4%22N+76%C2%B048'42.9%22E/@8.6953942",
      "76.8093418",
      "17z/data=!3m1!4b1!4m4!3m3!8m2!3d8.6953889!4d76.8119167?entry=ttu"
    ],
    "common_details": {
      "wifi": "Yes",
      "washing_machines": "Yes",
      "filtered_water": "Yes",
      "hot_water": "No",
      "parking": "Yes",
      "security": "Yes",
      "cctv": "Yes",
      "iron_box": "Yes",
      "common_bathroom": "Yes",
      "NOTA": "No"
    },
    "single_room": {
      "available": "Yes",
      "price": "--",
      "bed_type": {
        "single": {
          "available": "No"
        },
        "double": {
          "available": "No"
        }
      },
      "options_available": {
        "ac": "No",
        "furniture": "Yes",
        "private_bathroom": "Yes"
      }
    },
    "shared_room": {
      "available": "Yes",
      "price": "5500",
      "bed_type": {
        "single": {
          "available": "Yes"
        },
        "double": {
          "available": "No"
        }
      },
      "options_available": {
        "ac": "No",
        "furniture": "Yes",
        "private_bathroom": "Yes"
      }
    }
  },
  {
    "id": 9,
    "hostel_name": "Shared Home For Girls - Moonumukku",
    "owner_name": "",
    "price": "",
    "contact_no": "7356455367",
    "whatsapp_no": "7356455367",
    "food": "",
    "deposit": "",
    "distance": "1.5 kms",
    "gender": "Female",
    "seats": {
      "girls": ""
    },
    "images": [
      "moonumukku (1).jpg",
      "moonumukku (2).jpg",
      "moonumukku (3).jpg",
      "moonumukku (4).jpg"
    ],
    "links": [],
    "common_details": {
      "wifi": "Yes",
      "washing_machines": "No",
      "filtered_water": "No",
      "hot_water": "No",
      "parking": "Yes",
      "security": "Yes",
      "cctv": "Yes",
      "iron_box": "No",
      "common_bathroom": "Yes",
      "NOTA": "No"
    },
    "single_room": {
      "available": "No",
      "price": "N/A",
      "bed_type": {
        "single": {
          "available": "No"
        },
        "double": {
          "available": "No"
        }
      },
      "options_available": {
        "ac": "No",
        "furniture": "No",
        "private_bathroom": "No"
      }
    },
    "shared_room": {
      "available": "Yes",
      "price": "",
      "bed_type": {
        "single": {
          "available": "Yes"
        },
        "double": {
          "available": "No"
        }
      },
      "options_available": {
        "ac": "No",
        "furniture": "Yes",
        "private_bathroom": "No"
      }
    }
  }
]
